LICENSE
README.md
setup.py
arguing/__init__.py
arguing/parser.py
arguing.egg-info/PKG-INFO
arguing.egg-info/SOURCES.txt
arguing.egg-info/dependency_links.txt
arguing.egg-info/top_level.txt