Metadata-Version: 2.1
Name: arguing
Version: 1.3.7
Summary: Create nice CLIs without bloating your apps.
Home-page: https://github.com/ZSendokame/arguing
Author: Sendokame
License: UNKNOWN
Platform: UNKNOWN
License-File: LICENSE
